rainbowlog/__init__.py
rainbowlog/_formatter.py
rainbowlog/py.typed
rainbowlog-2.1.0.dist-info/METADATA
rainbowlog-2.1.0.dist-info/WHEEL
rainbowlog-2.1.0.dist-info/licenses/LICENSE
rainbowlog-2.1.0.dist-info/RECORD
