Metadata-Version: 2.4
Name: rainbowlog
Version: 2.1.0
Summary: Format your python logs with colours based on the log levels.
Project-URL: homepage, https://github.com/abrahammurciano/rainbowlog
Project-URL: documentation, https://abrahammurciano.github.io/rainbowlog/rainbowlog/
Project-URL: repository, https://github.com/abrahammurciano/rainbowlog
Author-email: Abraham Murciano <abrahammurciano@gmail.com>
License-Expression: MIT
License-File: LICENSE
Keywords: color,logging
Requires-Python: >=3.8
Requires-Dist: constyle>=2.0.5
